glycoforge/__init__.py
glycoforge/pipeline.py
glycoforge/sim_batch_factor.py
glycoforge/sim_bio_factor.py
glycoforge/utils.py
glycoforge/sample_config/hybrid_mode_config.yaml
glycoforge/sample_config/simlified_mode_config.yaml
glycoforge-0.1.2.dist-info/licenses/LICENSE
glycoforge-0.1.2.dist-info/METADATA
glycoforge-0.1.2.dist-info/WHEEL
glycoforge-0.1.2.dist-info/top_level.txt
glycoforge-0.1.2.dist-info/RECORD
