Metadata-Version: 2.4
Name: glycoforge
Version: 0.1.2
Summary: A simulation tool for generating glycomic relative abundance datasets with customizable biological group differences and controllable batch-effect injection
Author-email: "Zoe (Siyu) Hu" <zoe.sy.hu@gmail.com>, Daniel Bojar <daniel.bojar@gu.se>
License: MIT
Project-URL: Homepage, https://github.com/BojarLab/GlycoForge
Project-URL: Repository, https://github.com/BojarLab/GlycoForge
Project-URL: Documentation, https://github.com/BojarLab/GlycoForge#readme
Project-URL: Bug Tracker, https://github.com/BojarLab/GlycoForge/issues
Keywords: glycomics,simulation,relative-abundance data,batch-effect,compositional-data,bioinformatics,MNAR
Classifier: Development Status :: 3 - Alpha
Classifier: Intended Audience :: Science/Research
Classifier: Topic :: Scientific/Engineering :: Bio-Informatics
Classifier: License :: OSI Approved :: MIT License
Classifier: Programming Language :: Python :: 3
Classifier: Programming Language :: Python :: 3.10
Classifier: Operating System :: OS Independent
Requires-Python: <3.13,>=3.10
License-File: LICENSE
Requires-Dist: numpy>=1.21.0
Requires-Dist: pandas>=1.3.0
Requires-Dist: scipy>=1.7.0
Requires-Dist: scikit-learn>=1.0.0
Requires-Dist: matplotlib>=3.5.0
Requires-Dist: seaborn>=0.11.0
Requires-Dist: glycowork>=1.6.4
Provides-Extra: dev
Requires-Dist: pytest>=7.0.0; extra == "dev"
Requires-Dist: jupyter>=1.0.0; extra == "dev"
Requires-Dist: notebook>=6.4.0; extra == "dev"
Dynamic: license-file
